README
setup.py
radlocate/__init__.py
radlocate/radlocate.py
radlocate.egg-info/PKG-INFO
radlocate.egg-info/SOURCES.txt
radlocate.egg-info/dependency_links.txt
radlocate.egg-info/not-zip-safe
radlocate.egg-info/top_level.txt