Metadata-Version: 1.0
Name: radlocate
Version: 0.1
Summary: Lat/Lon Location tools
Home-page: https://github.com/brdly-smith/radlocate
Author: Brad Smith
Author-email: sl1ck731@gmail.com
License: MIT
Platform: UNKNOWN
